swa_cc/core/__init__.py
swa_cc.core-1.3.0.dist-info/METADATA
swa_cc.core-1.3.0.dist-info/WHEEL
swa_cc.core-1.3.0.dist-info/top_level.txt
swa_cc.core-1.3.0.dist-info/RECORD
